[
  {
    "filename": "SA-11-22-DSCF6210.jpg",
    "url": "/Website%20beloveful.com/Africa/South%20Africa/SA-11-22-DSCF6210.jpg",
    "size": 710654
  },
  {
    "filename": "SA-11-22-DSCF5766.jpg",
    "url": "/Website%20beloveful.com/Africa/South%20Africa/SA-11-22-DSCF5766.jpg",
    "size": 752375
  },
  {
    "filename": "SA-11-22-DSCF6247.jpg",
    "url": "/Website%20beloveful.com/Africa/South%20Africa/SA-11-22-DSCF6247.jpg",
    "size": 584134
  },
  {
    "filename": "SA-11-22-DSCF6237.jpg",
    "url": "/Website%20beloveful.com/Africa/South%20Africa/SA-11-22-DSCF6237.jpg",
    "size": 649351
  },
  {
    "filename": "SA-11-22-DSCF5838.jpg",
    "url": "/Website%20beloveful.com/Africa/South%20Africa/SA-11-22-DSCF5838.jpg",
    "size": 754018
  },
  {
    "filename": "DSCF6243.jpg",
    "url": "/Website%20beloveful.com/Africa/South%20Africa/DSCF6243.jpg",
    "size": 1364583
  },
  {
    "filename": "SA-11-22-DSCF5780.jpg",
    "url": "/Website%20beloveful.com/Africa/South%20Africa/SA-11-22-DSCF5780.jpg",
    "size": 779965
  },
  {
    "filename": "DSCF6215.jpg",
    "url": "/Website%20beloveful.com/Africa/South%20Africa/DSCF6215.jpg",
    "size": 1949648
  },
  {
    "filename": "SA-11-22-DSCF5770.jpg",
    "url": "/Website%20beloveful.com/Africa/South%20Africa/SA-11-22-DSCF5770.jpg",
    "size": 668876
  },
  {
    "filename": "SA-11-22-DSCF6201.jpg",
    "url": "/Website%20beloveful.com/Africa/South%20Africa/SA-11-22-DSCF6201.jpg",
    "size": 614190
  },
  {
    "filename": "SA-11-22-DSCF6142.jpg",
    "url": "/Website%20beloveful.com/Africa/South%20Africa/SA-11-22-DSCF6142.jpg",
    "size": 772890
  },
  {
    "filename": "SA-11-22-DSCF5932.jpg",
    "url": "/Website%20beloveful.com/Africa/South%20Africa/SA-11-22-DSCF5932.jpg",
    "size": 669074
  },
  {
    "filename": "SA-11-22-DSCF5926.jpg",
    "url": "/Website%20beloveful.com/Africa/South%20Africa/SA-11-22-DSCF5926.jpg",
    "size": 638111
  },
  {
    "filename": "SA-11-22-DSCF5864.jpg",
    "url": "/Website%20beloveful.com/Africa/South%20Africa/SA-11-22-DSCF5864.jpg",
    "size": 770781
  },
  {
    "filename": "SA-11-22-DSCF5758.jpg",
    "url": "/Website%20beloveful.com/Africa/South%20Africa/SA-11-22-DSCF5758.jpg",
    "size": 771621
  },
  {
    "filename": "SA-11-22-DSCF5894.jpg",
    "url": "/Website%20beloveful.com/Africa/South%20Africa/SA-11-22-DSCF5894.jpg",
    "size": 636483
  }
]